matmov/__init__.py
matmov/erros.py
matmov/funcoesmod.py
matmov/matmov.py
matmov/presolver.py
matmov/resultados.py
matmov-1.1.0.dist-info/LICENSE
matmov-1.1.0.dist-info/METADATA
matmov-1.1.0.dist-info/WHEEL
matmov-1.1.0.dist-info/top_level.txt
matmov-1.1.0.dist-info/RECORD
