Metadata-Version: 2.1
Name: matmov
Version: 1.1.0
Summary: Solver para o problema de alocação de alunos na ONG Matemática em Movimento
Home-page: https://github.com/gabpassos/matmov
Author: Gabriel Passos, Flávia C. Gachet
Author-email: gabrielpassos97@hotmail.com
License: MIT
Platform: UNKNOWN
Classifier: Development Status :: 4 - Beta
Classifier: License :: OSI Approved :: MIT License
Classifier: Environment :: Console
Classifier: Programming Language :: Python :: 3
Classifier: Programming Language :: Python :: 3.7
Classifier: Programming Language :: Python :: 3.8
Classifier: Operating System :: OS Independent
Requires-Python: >=3.7
Requires-Dist: ortools (>=8.0.0)
Requires-Dist: pandas (<2.*,>=1.1.2)
Requires-Dist: numpy (<2.*,>=1.19.2)
Requires-Dist: matplotlib (<4.*,>=3.3.2)
